EcoleDirectePy/__init__.py
EcoleDirectePy/main.py
EcoleDirectePy-0.0.5.dist-info/LICENSE
EcoleDirectePy-0.0.5.dist-info/METADATA
EcoleDirectePy-0.0.5.dist-info/WHEEL
EcoleDirectePy-0.0.5.dist-info/top_level.txt
EcoleDirectePy-0.0.5.dist-info/RECORD
