Metadata-Version: 2.1
Name: EcoleDirectePy
Version: 0.0.5
Summary: a API Wrapper for EcoleDirecte.fr
Home-page: https://github.com/germaindk/EcoleDirectePy
Author: DK16
Author-email: <dk16v2@gmail.com>
Keywords: python,ecoledirecte,api,Wrapper
License-File: LICENSE
Requires-Dist: requests
